[
  {
    "sha256": "9bbef19476623ca56c17da75fd57734dbf82530686043a6e491c6d71befe8f6e",
    "reason": "Documented synthetic payment test number used only by the isolated fake gateway.",
    "owner": "maintainer",
    "expiresAt": "2027-07-13T00:00:00.000Z"
  },
  {
    "sha256": "03a3abf2e050aa3a1b7716235c74f465ed52ba71ca03a42a407b2815e651ee1e",
    "reason": "Documented fake control-plane token used only by isolated regression tests.",
    "owner": "maintainer",
    "expiresAt": "2027-07-13T00:00:00.000Z"
  },
  {
    "sha256": "6098ef32fadfde15e789741e5dfdc5fc8190c3353f0c280129ab824defb5dfff",
    "reason": "Documented invalid session-cookie fixture used by negative authentication tests.",
    "owner": "maintainer",
    "expiresAt": "2027-07-13T00:00:00.000Z"
  }
]
